{
   "variant": "rapidapi_basic",
   "id": "tt1327035",
   "collection": {
      "locations": [
         {
            "display_name": "Netflix",
            "id": "5d81fe2fd51bef0f42268f0f",
            "url": "https://www.netflix.com/title/70113305",
            "name": "NetflixIVAUS",
            "icon": "https://utellyassets7.imgix.net/locations_icons/utelly/black_new/NetflixIVAUS.png?w=92&auto=compress&app_version=4b332051-9795-4332-8447-e80ba4f0bb9c_1e1210o12022-11-15"
         }
      ],
      "source_ids": {
         "imdb": {
            "url": "https://www.imdb.com/title/tt1327035",
            "id": "tt1327035"
         }
      },
      "id": "5e2ce07690c0e033a487df02",
      "weight": 0,
      "picture": "https://utellyassets9-2.imgix.net/api/Images/96563697b7318d7121f3bac1e6e3f34e/Redirect?fit=crop&auto=compress&crop=faces,top",
      "name": "Dev.D"
   },
   "status_code": 200,
   "type": "imdb"
}