{
   "imdbID": "tt0756683",
   "tmdbID": "13363",
   "imdbRating": 79,
   "imdbVoteCount": 188225,
   "tmdbRating": 76,
   "backdropPath": "/gt4EnUGbbGbNOX0q47YII3WxB48.jpg",
   "backdropURLs": {
      "300": "https://image.tmdb.org/t/p/w300/gt4EnUGbbGbNOX0q47YII3WxB48.jpg",
      "780": "https://image.tmdb.org/t/p/w780/gt4EnUGbbGbNOX0q47YII3WxB48.jpg",
      "1280": "https://image.tmdb.org/t/p/w1280/gt4EnUGbbGbNOX0q47YII3WxB48.jpg",
      "original": "https://image.tmdb.org/t/p/original/gt4EnUGbbGbNOX0q47YII3WxB48.jpg"
   },
   "originalTitle": "The Man from Earth",
   "genres": [
      18,
      14,
      9648
   ],
   "countries": [
      "US"
   ],
   "year": 2007,
   "runtime": 87,
   "cast": [
      "David Lee Smith",
      "Tony Todd",
      "John Billingsley",
      "Ellen Crawford",
      "Annika Peterson",
      "Alexis Thorpe",
      "William Katt"
   ],
   "significants": [
      "Richard Schenkman"
   ],
   "title": "The Man from Earth",
   "overview": "An impromptu goodbye party for Professor John Oldman becomes a mysterious interrogation after the retiring scholar reveals to his colleagues he never ages and has walked the earth for 14,000 years.",
   "tagline": "From one of the acclaimed writers of Star Trek and The Twilight Zone comes a story that transcends both time and space...",
   "video": "9mOIxyRTY5I",
   "posterPath": "/V086R82gNgWrotaXZFO4JhdgB1.jpg",
   "posterURLs": {
      "92": "https://image.tmdb.org/t/p/w92/V086R82gNgWrotaXZFO4JhdgB1.jpg",
      "154": "https://image.tmdb.org/t/p/w154/V086R82gNgWrotaXZFO4JhdgB1.jpg",
      "185": "https://image.tmdb.org/t/p/w185/V086R82gNgWrotaXZFO4JhdgB1.jpg",
      "342": "https://image.tmdb.org/t/p/w342/V086R82gNgWrotaXZFO4JhdgB1.jpg",
      "500": "https://image.tmdb.org/t/p/w500/V086R82gNgWrotaXZFO4JhdgB1.jpg",
      "780": "https://image.tmdb.org/t/p/w780/V086R82gNgWrotaXZFO4JhdgB1.jpg",
      "original": "https://image.tmdb.org/t/p/original/V086R82gNgWrotaXZFO4JhdgB1.jpg"
   },
   "age": 8,
   "streamingInfo": {},
   "originalLanguage": "en"
}