{
   "imdbID": "tt5362988",
   "tmdbID": "395834",
   "imdbRating": 77,
   "imdbVoteCount": 251779,
   "tmdbRating": 74,
   "backdropPath": "/kQGxGXzYiCumY8kmXXpgbZyZQK8.jpg",
   "backdropURLs": {
      "300": "https://image.tmdb.org/t/p/w300/kQGxGXzYiCumY8kmXXpgbZyZQK8.jpg",
      "780": "https://image.tmdb.org/t/p/w780/kQGxGXzYiCumY8kmXXpgbZyZQK8.jpg",
      "1280": "https://image.tmdb.org/t/p/w1280/kQGxGXzYiCumY8kmXXpgbZyZQK8.jpg",
      "original": "https://image.tmdb.org/t/p/original/kQGxGXzYiCumY8kmXXpgbZyZQK8.jpg"
   },
   "originalTitle": "Wind River",
   "genres": [
      80,
      18,
      9648
   ],
   "countries": [
      "FR",
      "GB",
      "US"
   ],
   "year": 2017,
   "runtime": 107,
   "cast": [
      "Jeremy Renner",
      "Elizabeth Olsen",
      "Gil Birmingham",
      "Kelsey Asbille",
      "Teo Briones",
      "Tantoo Cardinal",
      "Matthew Del Negro"
   ],
   "significants": [
      "Taylor Sheridan"
   ],
   "title": "Wind River",
   "overview": "An FBI agent teams with the town's veteran game tracker to investigate a murder that occurred on a Native American reservation.",
   "tagline": "Nothing is harder to track than the truth.",
   "video": "CZgN0dpFoaE",
   "posterPath": "/pySivdR845Hom4u4T2WNkJxe6Ad.jpg",
   "posterURLs": {
      "92": "https://image.tmdb.org/t/p/w92/pySivdR845Hom4u4T2WNkJxe6Ad.jpg",
      "154": "https://image.tmdb.org/t/p/w154/pySivdR845Hom4u4T2WNkJxe6Ad.jpg",
      "185": "https://image.tmdb.org/t/p/w185/pySivdR845Hom4u4T2WNkJxe6Ad.jpg",
      "342": "https://image.tmdb.org/t/p/w342/pySivdR845Hom4u4T2WNkJxe6Ad.jpg",
      "500": "https://image.tmdb.org/t/p/w500/pySivdR845Hom4u4T2WNkJxe6Ad.jpg",
      "780": "https://image.tmdb.org/t/p/w780/pySivdR845Hom4u4T2WNkJxe6Ad.jpg",
      "original": "https://image.tmdb.org/t/p/original/pySivdR845Hom4u4T2WNkJxe6Ad.jpg"
   },
   "age": 16,
   "streamingInfo": {},
   "originalLanguage": "en"
}