{
   "movie_results": [
      {
         "adult": false,
         "backdrop_path": "/AdKA2F1SzYPhSZdEbjH1Zh75UVQ.jpg",
         "id": 694,
         "title": "The Shining",
         "original_language": "en",
         "original_title": "The Shining",
         "overview": "Jack Torrance accepts a caretaker job at the Overlook Hotel, where he, along with his wife Wendy and their son Danny, must live isolated from the rest of the world for the winter. But they aren't prepared for the madness that lurks within.",
         "poster_path": "/nRj5511mZdTl4saWEPoj9QroTIu.jpg",
         "media_type": "movie",
         "genre_ids": [
            27,
            53
         ],
         "popularity": 51.297,
         "release_date": "1980-05-23",
         "video": false,
         "vote_average": 8.224,
         "vote_count": 15082
      }
   ],
   "person_results": [],
   "tv_results": [],
   "tv_episode_results": [],
   "tv_season_results": []
}