{
   "movie_results": [
      {
         "adult": false,
         "backdrop_path": "/mpNd0rTVrp6vHJ9Je7wSa3zC8JS.jpg",
         "id": 128,
         "title": "Princess Mononoke",
         "original_language": "ja",
         "original_title": "もののけ姫",
         "overview": "Ashitaka, a prince of the disappearing Emishi people, is cursed by a demonized boar god and must journey to the west to find a cure. Along the way, he encounters San, a young human woman fighting to protect the forest, and Lady Eboshi, who is trying to destroy it. Ashitaka must find a way to bring balance to this conflict.",
         "poster_path": "/cMYCDADoLKLbB83g4WnJegaZimC.jpg",
         "media_type": "movie",
         "genre_ids": [
            12,
            14,
            16
         ],
         "popularity": 39.779,
         "release_date": "1997-07-12",
         "video": false,
         "vote_average": 8.348,
         "vote_count": 6638
      }
   ],
   "person_results": [],
   "tv_results": [],
   "tv_episode_results": [],
   "tv_season_results": []
}