{
   "variant": "rapidapi_basic",
   "id": "tt0013442",
   "collection": {
      "locations": [
         {
            "display_name": "Amazon Instant Video",
            "id": "5d82609332ac2f0051962fe6",
            "url": "https://www.amazon.com/gp/video/detail/B014LG7M9K/ref=atv_sr_def_c_unkc_14_1_14?sr=1-14&pageTypeIdSource=ASIN&pageTypeId=B01CJQ68OE&qid=1656048113&tag=utellycom00-21",
            "name": "AmazonInstantVideoIVAUS",
            "icon": "https://utellyassets7.imgix.net/locations_icons/utelly/black_new/AmazonInstantVideoIVAUS.png?w=92&auto=compress&app_version=4b332051-9795-4332-8447-e80ba4f0bb9c_1e1210o12022-11-15"
         },
         {
            "display_name": "Google Play",
            "id": "5d8260b128fbcd0052aed197",
            "url": "https://play.google.com/store/movies/details/Nosferatu?id=e17pQ8d77qE&hl=en&gl=US",
            "name": "GooglePlayIVAUS",
            "icon": "https://utellyassets7.imgix.net/locations_icons/utelly/black_new/GooglePlayIVAUS.png?w=92&auto=compress&app_version=4b332051-9795-4332-8447-e80ba4f0bb9c_1e1210o12022-11-15"
         },
         {
            "display_name": "iTunes",
            "id": "5d80a9a5d51bef861d3740d3",
            "url": "https://itunes.apple.com/us/movie/nosferatu-remastered/id918711927?uo=4",
            "name": "iTunesIVAUS",
            "icon": "https://utellyassets7.imgix.net/locations_icons/utelly/black_new/iTunesIVAUS.png?w=92&auto=compress&app_version=4b332051-9795-4332-8447-e80ba4f0bb9c_1e1210o12022-11-15"
         }
      ],
      "source_ids": {
         "imdb": {
            "url": "https://www.imdb.com/title/tt0013442",
            "id": "tt0013442"
         }
      },
      "id": "5d97d9f49a76a40056de0e1b",
      "weight": 0,
      "picture": "https://utellyassets9-1.imgix.net/api/Images/aa0dba7c4aa6c607637d5fb94f682dca/Redirect?fit=crop&auto=compress&crop=faces,top",
      "name": "Nosferatu"
   },
   "status_code": 200,
   "type": "imdb"
}