{
   "imdbID": "tt0043265",
   "tmdbID": "488",
   "imdbRating": 77,
   "imdbVoteCount": 79248,
   "tmdbRating": 73,
   "backdropPath": "/gwe1k68ZFxEo8ZqqR73oobiQwK4.jpg",
   "backdropURLs": {
      "300": "https://image.tmdb.org/t/p/w300/gwe1k68ZFxEo8ZqqR73oobiQwK4.jpg",
      "780": "https://image.tmdb.org/t/p/w780/gwe1k68ZFxEo8ZqqR73oobiQwK4.jpg",
      "1280": "https://image.tmdb.org/t/p/w1280/gwe1k68ZFxEo8ZqqR73oobiQwK4.jpg",
      "original": "https://image.tmdb.org/t/p/original/gwe1k68ZFxEo8ZqqR73oobiQwK4.jpg"
   },
   "originalTitle": "The African Queen",
   "genres": [
      12,
      10749
   ],
   "countries": [
      "GB",
      "US"
   ],
   "year": 1952,
   "runtime": 105,
   "cast": [
      "Humphrey Bogart",
      "Katharine Hepburn",
      "Robert Morley",
      "Peter Bull",
      "Theodore Bikel",
      "Walter Gotell",
      "Peter Swanwick"
   ],
   "significants": [
      "John Huston"
   ],
   "title": "The African Queen",
   "overview": "At the start of the First World War, in the middle of Africa’s nowhere, a gin soaked riverboat captain is persuaded by a strong-willed missionary to go down river and face-off a German warship.",
   "tagline": "The greatest adventure a man ever lived… with a woman!",
   "video": "WIzI_zWPbXM",
   "posterPath": "/2Ypg0KhQfFYWILelvHGtSHHR0dk.jpg",
   "posterURLs": {
      "92": "https://image.tmdb.org/t/p/w92/2Ypg0KhQfFYWILelvHGtSHHR0dk.jpg",
      "154": "https://image.tmdb.org/t/p/w154/2Ypg0KhQfFYWILelvHGtSHHR0dk.jpg",
      "185": "https://image.tmdb.org/t/p/w185/2Ypg0KhQfFYWILelvHGtSHHR0dk.jpg",
      "342": "https://image.tmdb.org/t/p/w342/2Ypg0KhQfFYWILelvHGtSHHR0dk.jpg",
      "500": "https://image.tmdb.org/t/p/w500/2Ypg0KhQfFYWILelvHGtSHHR0dk.jpg",
      "780": "https://image.tmdb.org/t/p/w780/2Ypg0KhQfFYWILelvHGtSHHR0dk.jpg",
      "original": "https://image.tmdb.org/t/p/original/2Ypg0KhQfFYWILelvHGtSHHR0dk.jpg"
   },
   "age": 5,
   "streamingInfo": {},
   "originalLanguage": "en"
}