{
   "imdbID": "tt0112384",
   "tmdbID": "568",
   "imdbRating": 77,
   "imdbVoteCount": 295856,
   "tmdbRating": 74,
   "backdropPath": "/32zua2oKjn2EaRk7am3qK8zAlEj.jpg",
   "backdropURLs": {
      "300": "https://image.tmdb.org/t/p/w300/32zua2oKjn2EaRk7am3qK8zAlEj.jpg",
      "780": "https://image.tmdb.org/t/p/w780/32zua2oKjn2EaRk7am3qK8zAlEj.jpg",
      "1280": "https://image.tmdb.org/t/p/w1280/32zua2oKjn2EaRk7am3qK8zAlEj.jpg",
      "original": "https://image.tmdb.org/t/p/original/32zua2oKjn2EaRk7am3qK8zAlEj.jpg"
   },
   "originalTitle": "Apollo 13",
   "genres": [
      12,
      18,
      36
   ],
   "countries": [
      "US"
   ],
   "year": 1995,
   "runtime": 140,
   "cast": [
      "Tom Hanks",
      "Bill Paxton",
      "Kevin Bacon",
      "Gary Sinise",
      "Ed Harris",
      "Kathleen Quinlan",
      "Roger Corman"
   ],
   "significants": [
      "Ron Howard"
   ],
   "title": "Apollo 13",
   "overview": "The true story of technical troubles that scuttle the Apollo 13 lunar mission in 1970, risking the lives of astronaut Jim Lovell and his crew, with the failed journey turning into a thrilling saga of heroism. Drifting more than 200,000 miles from Earth, the astronauts work furiously with the ground crew to avert tragedy.",
   "tagline": "Houston, we have a problem.",
   "video": "KtEIMC58sZo",
   "posterPath": "/oYUZHYMwNKnE1ef4WE5Hw2a9OAY.jpg",
   "posterURLs": {
      "92": "https://image.tmdb.org/t/p/w92/oYUZHYMwNKnE1ef4WE5Hw2a9OAY.jpg",
      "154": "https://image.tmdb.org/t/p/w154/oYUZHYMwNKnE1ef4WE5Hw2a9OAY.jpg",
      "185": "https://image.tmdb.org/t/p/w185/oYUZHYMwNKnE1ef4WE5Hw2a9OAY.jpg",
      "342": "https://image.tmdb.org/t/p/w342/oYUZHYMwNKnE1ef4WE5Hw2a9OAY.jpg",
      "500": "https://image.tmdb.org/t/p/w500/oYUZHYMwNKnE1ef4WE5Hw2a9OAY.jpg",
      "780": "https://image.tmdb.org/t/p/w780/oYUZHYMwNKnE1ef4WE5Hw2a9OAY.jpg",
      "original": "https://image.tmdb.org/t/p/original/oYUZHYMwNKnE1ef4WE5Hw2a9OAY.jpg"
   },
   "age": 6,
   "streamingInfo": {
      "starz": {
         "us": {
            "link": "https://www.starz.com/us/en/movies/44587",
            "added": 1667594788,
            "leaving": 32503697999
         }
      }
   },
   "originalLanguage": "en"
}