{
   "imdbID": "tt0344510",
   "tmdbID": "2841",
   "imdbRating": 76,
   "imdbVoteCount": 74100,
   "tmdbRating": 73,
   "backdropPath": "/xdxnl5x8it3vLIaivaMP4h5NJNq.jpg",
   "backdropURLs": {
      "300": "https://image.tmdb.org/t/p/w300/xdxnl5x8it3vLIaivaMP4h5NJNq.jpg",
      "780": "https://image.tmdb.org/t/p/w780/xdxnl5x8it3vLIaivaMP4h5NJNq.jpg",
      "1280": "https://image.tmdb.org/t/p/w1280/xdxnl5x8it3vLIaivaMP4h5NJNq.jpg",
      "original": "https://image.tmdb.org/t/p/original/xdxnl5x8it3vLIaivaMP4h5NJNq.jpg"
   },
   "originalTitle": "Un long dimanche de fiançailles",
   "genres": [
      18,
      9648,
      10749
   ],
   "countries": [
      "FR"
   ],
   "year": 2004,
   "runtime": 133,
   "cast": [
      "Audrey Tautou",
      "Gaspard Ulliel",
      "Dominique Pinon",
      "Chantal Neuwirth",
      "André Dussollier",
      "Ticky Holgado",
      "Marion Cotillard"
   ],
   "significants": [
      "Jean-Pierre Jeunet"
   ],
   "title": "A Very Long Engagement",
   "overview": "Young Frenchwoman Mathilde searches for the truth about her missing fiancé, lost during World War I, and learns many unexpected things along the way. The love of her life is gone. But she refuses to believe he's gone forever — and she needs to know for sure.",
   "tagline": "Never let go.",
   "video": "2HJXPvM1y2E",
   "posterPath": "/t73m7lX0eFYDjlB1Gcb7r3S5Yt.jpg",
   "posterURLs": {
      "92": "https://image.tmdb.org/t/p/w92/t73m7lX0eFYDjlB1Gcb7r3S5Yt.jpg",
      "154": "https://image.tmdb.org/t/p/w154/t73m7lX0eFYDjlB1Gcb7r3S5Yt.jpg",
      "185": "https://image.tmdb.org/t/p/w185/t73m7lX0eFYDjlB1Gcb7r3S5Yt.jpg",
      "342": "https://image.tmdb.org/t/p/w342/t73m7lX0eFYDjlB1Gcb7r3S5Yt.jpg",
      "500": "https://image.tmdb.org/t/p/w500/t73m7lX0eFYDjlB1Gcb7r3S5Yt.jpg",
      "780": "https://image.tmdb.org/t/p/w780/t73m7lX0eFYDjlB1Gcb7r3S5Yt.jpg",
      "original": "https://image.tmdb.org/t/p/original/t73m7lX0eFYDjlB1Gcb7r3S5Yt.jpg"
   },
   "age": -1,
   "streamingInfo": {},
   "originalLanguage": "fr"
}