{
   "imdbID": "tt0475276",
   "tmdbID": "9829",
   "imdbRating": 76,
   "imdbVoteCount": 106984,
   "tmdbRating": 71,
   "backdropPath": "/pbm04tWNa8MkbPqJ33yrGVXTWAl.jpg",
   "backdropURLs": {
      "300": "https://image.tmdb.org/t/p/w300/pbm04tWNa8MkbPqJ33yrGVXTWAl.jpg",
      "780": "https://image.tmdb.org/t/p/w780/pbm04tWNa8MkbPqJ33yrGVXTWAl.jpg",
      "1280": "https://image.tmdb.org/t/p/w1280/pbm04tWNa8MkbPqJ33yrGVXTWAl.jpg",
      "original": "https://image.tmdb.org/t/p/original/pbm04tWNa8MkbPqJ33yrGVXTWAl.jpg"
   },
   "originalTitle": "United 93",
   "genres": [
      28,
      18,
      36
   ],
   "countries": [
      "FR",
      "GB",
      "US"
   ],
   "year": 2006,
   "runtime": 111,
   "cast": [
      "Trieste Kelly Dunn",
      "Starla Benford",
      "Kate Jennings Grant",
      "J.J. Johnson",
      "Polly Adams",
      "Trish Gates",
      "Olivia Thirlby"
   ],
   "significants": [
      "Paul Greengrass"
   ],
   "title": "United 93",
   "overview": "A real-time account of the events on United Flight 93, one of the planes hijacked on 9/11 that crashed near Shanksville, Pennsylvania when passengers foiled the terrorist plot.",
   "tagline": "September 11, 2001. Four planes were hijacked. Three of them reached their target. This is the story of the fourth.",
   "video": "kHdqw6scuIc",
   "posterPath": "/aahr1uIPrEej8q4baE1RYXOXwFB.jpg",
   "posterURLs": {
      "92": "https://image.tmdb.org/t/p/w92/aahr1uIPrEej8q4baE1RYXOXwFB.jpg",
      "154": "https://image.tmdb.org/t/p/w154/aahr1uIPrEej8q4baE1RYXOXwFB.jpg",
      "185": "https://image.tmdb.org/t/p/w185/aahr1uIPrEej8q4baE1RYXOXwFB.jpg",
      "342": "https://image.tmdb.org/t/p/w342/aahr1uIPrEej8q4baE1RYXOXwFB.jpg",
      "500": "https://image.tmdb.org/t/p/w500/aahr1uIPrEej8q4baE1RYXOXwFB.jpg",
      "780": "https://image.tmdb.org/t/p/w780/aahr1uIPrEej8q4baE1RYXOXwFB.jpg",
      "original": "https://image.tmdb.org/t/p/original/aahr1uIPrEej8q4baE1RYXOXwFB.jpg"
   },
   "age": 14,
   "streamingInfo": {},
   "originalLanguage": "en"
}